LICENSE
README.md
setup.py
Saker.egg-info/PKG-INFO
Saker.egg-info/SOURCES.txt
Saker.egg-info/dependency_links.txt
Saker.egg-info/requires.txt
Saker.egg-info/top_level.txt
saker/__init__.py
saker/__main__.py
saker/api/__init__.py
saker/api/censys.py
saker/api/crtsh.py
saker/api/dingtalk.py
saker/api/dnsdumpster.py
saker/api/fofa.py
saker/api/gaode.py
saker/api/githubapi.py
saker/api/icp.py
saker/api/proxypool.py
saker/api/rwhois.py
saker/api/shodanapi.py
saker/api/sqlmap.py
saker/api/threatcrowd.py
saker/api/whois.py
saker/brute/__init__.py
saker/brute/basicAuth.py
saker/brute/brute.py
saker/brute/brute_win.py
saker/brute/cs.py
saker/brute/dir.py
saker/brute/domain.py
saker/brute/email.py
saker/brute/ftp.py
saker/brute/mysql.py
saker/brute/smtp.py
saker/brute/ssh.py
saker/brute/telnet.py
saker/brute/zip.py
saker/cmdline/__init__.py
saker/cmdline/file.py
saker/cmdline/fuzz.py
saker/cmdline/fuzzsock.py
saker/cmdline/poc.py
saker/cmdline/port.py
saker/cmdline/scan.py
saker/cmdline/server.py
saker/cmdline/util.py
saker/core/__init__.py
saker/core/mutator.py
saker/core/poc.py
saker/core/rawhttp.py
saker/core/request.py
saker/core/scaner.py
saker/core/sess.py
saker/core/sock.py
saker/data/__init__.py
saker/data/banner.py
saker/data/sort.py
saker/db/__init__.py
saker/db/mysql.py
saker/db/sqlite.py
saker/fuzzers/__init__.py
saker/fuzzers/bof.py
saker/fuzzers/cmdi.py
saker/fuzzers/code.py
saker/fuzzers/cookie.py
saker/fuzzers/cors.py
saker/fuzzers/crlf.py
saker/fuzzers/dos.py
saker/fuzzers/fileinclude.py
saker/fuzzers/fmtstr.py
saker/fuzzers/fuzzer.py
saker/fuzzers/http.py
saker/fuzzers/httpSmuggle.py
saker/fuzzers/image.py
saker/fuzzers/json.py
saker/fuzzers/jsonp.py
saker/fuzzers/jwt.py
saker/fuzzers/ldap.py
saker/fuzzers/mysqli.py
saker/fuzzers/nginx.py
saker/fuzzers/openredirect.py
saker/fuzzers/password.py
saker/fuzzers/psql.py
saker/fuzzers/sqli.py
saker/fuzzers/sqlite.py
saker/fuzzers/ssi.py
saker/fuzzers/ssrf.py
saker/fuzzers/ssti.py
saker/fuzzers/template.py
saker/fuzzers/typecasting.py
saker/fuzzers/url.py
saker/fuzzers/xss.py
saker/fuzzers/xxe.py
saker/handler/__init__.py
saker/handler/headerHandler.py
