Metadata-Version: 2.1
Name: Saker
Version: 1.0.11
Summary: Tool For Fuzz Web Applications
Home-page: https://github.com/LyleMi/Saker
Author: Lyle
Author-email: lylemi@126.com
License: GPLv3 Licence
Keywords: Web Security,Fuzz
Platform: any
